mpi_slingshot/__init__.py
mpi_slingshot/config.py
mpi_slingshot/interactive.py
mpi_slingshot/logos.py
mpi_slingshot/slingshot.py
mpi_slingshot/tab_completer.py
mpi_slingshot-0.1.3.data/scripts/slingshot
mpi_slingshot-0.1.3.dist-info/DESCRIPTION.rst
mpi_slingshot-0.1.3.dist-info/METADATA
mpi_slingshot-0.1.3.dist-info/RECORD
mpi_slingshot-0.1.3.dist-info/WHEEL
mpi_slingshot-0.1.3.dist-info/metadata.json
mpi_slingshot-0.1.3.dist-info/top_level.txt
