Metadata-Version: 2.0
Name: mpi-slingshot
Version: 0.1.3
Summary: SLINGSHOT: Python wrapper for MPI to "slingshot" a small Python or R function against the Goliath of Big Data
Home-page: https://github.com/quadrismegistus/mpi-slingshot
Author: Ryan Heuser
Author-email: heuser@stanford.edu
License: MPL-2.0
Platform: UNKNOWN
Requires-Dist: mpi4py (==3.0.0)
Requires-Dist: numpy (==1.15.3)
Requires-Dist: ujson (==1.35)
Requires-Dist: unicodecsv (==0.14.1)
